{
  "create_time": "2019-05-17T15:19:44.000Z",
  "display_name": "Typewriter Tracking Plan",
  "name": "workspaces/segment_prod/tracking-plans/rs_1LMmY55PRAqJrqPrGzyk2nlYuZ3",
  "rules": {
    "events": [
      {
        "description": "Fired when a CLI command is started.",
        "name": "Command Run",
        "rules": {
          "$schema": "http://json-schema.org/draft-07/schema#",
          "labels": {},
          "properties": {
            "context": {},
            "properties": {
              "type": "object"
            },
            "traits": {}
          },
          "type": "object"
        }
      },
      {
        "description": "Fired when an error is encountered.",
        "name": "Error",
        "rules": {
          "$schema": "http://json-schema.org/draft-07/schema#",
          "labels": {},
          "properties": {
            "context": {},
            "properties": {
              "type": "object"
            },
            "traits": {}
          },
          "type": "object"
        }
      }
    ],
    "group_traits": [],
    "identify_traits": []
  },
  "update_time": "2019-05-17T15:21:07.000Z"
}
